cai_data/__init__.py
cai_data-0.0.0.dist-info/WHEEL
cai_data-0.0.0.dist-info/METADATA
cai_data-0.0.0.dist-info/RECORD
