Metadata-Version: 2.1
Name: cai-data
Version: 0.0.0
Summary: A data engineering package for Causal AI.
Author: causaLens
Author-email: opensource@causalens.com
Requires-Python: >=3.8,<4.0
Classifier: Programming Language :: Python :: 3
Classifier: Programming Language :: Python :: 3.8
Classifier: Programming Language :: Python :: 3.9
Classifier: Programming Language :: Python :: 3.10
Classifier: Programming Language :: Python :: 3.11
